pylaunch/__init__.py
pylaunch/core.py
pylaunch/ssdp.py
pylaunch/xmlparse.py
pylaunch/dial/__init__.py
pylaunch/dial/main.py
pylaunch/roku/__init__.py
pylaunch/roku/keypress.py
pylaunch/roku/main.py
pylaunch/roku/remote/__init__.py
pylaunch/roku/remote/buttons.py
pylaunch/roku/remote/controller.py
pylaunch/roku/remote/keys.py
pylaunch/roku/remote/views.py
pylaunch-0.3.0.dist-info/LICENSE
pylaunch-0.3.0.dist-info/METADATA
pylaunch-0.3.0.dist-info/WHEEL
pylaunch-0.3.0.dist-info/entry_points.txt
pylaunch-0.3.0.dist-info/top_level.txt
pylaunch-0.3.0.dist-info/RECORD
