Metadata-Version: 2.1
Name: pylaunch
Version: 0.3.0
Summary: UNKNOWN
Home-page: https://github.com/Sandersland/pylaunch
Author: Steffen Andersland
Author-email: stefandersland@gmail.com
License: MIT
Keywords: dial,roku
Platform: UNKNOWN
Classifier: Programming Language :: Python :: 3.7
Classifier: License :: OSI Approved :: MIT License
Classifier: Operating System :: Microsoft :: Windows :: Windows 10
Requires-Dist: requests
Provides-Extra: dev
Requires-Dist: nose (==1.3.7) ; extra == 'dev'
Requires-Dist: twine (==3.1.1) ; extra == 'dev'
Requires-Dist: pre-commit (==2.0.1) ; extra == 'dev'
Requires-Dist: black (==19.10b0) ; extra == 'dev'
